kubernetes_py/K8sComponentStatus.py
kubernetes_py/K8sConfig.py
kubernetes_py/K8sConfigMap.py
kubernetes_py/K8sContainer.py
kubernetes_py/K8sCronJob.py
kubernetes_py/K8sDaemonSet.py
kubernetes_py/K8sDeployment.py
kubernetes_py/K8sEvent.py
kubernetes_py/K8sExceptions.py
kubernetes_py/K8sHorizontalPodAutoscaler.py
kubernetes_py/K8sJob.py
kubernetes_py/K8sNamespace.py
kubernetes_py/K8sNode.py
kubernetes_py/K8sObject.py
kubernetes_py/K8sPersistentVolume.py
kubernetes_py/K8sPersistentVolumeClaim.py
kubernetes_py/K8sPetSet.py
kubernetes_py/K8sPod.py
kubernetes_py/K8sReplicaSet.py
kubernetes_py/K8sReplicationController.py
kubernetes_py/K8sSecret.py
kubernetes_py/K8sService.py
kubernetes_py/K8sServiceAccount.py
kubernetes_py/K8sStatefulSet.py
kubernetes_py/K8sStorageClass.py
kubernetes_py/K8sVolume.py
kubernetes_py/K8sVolumeMount.py
kubernetes_py/__init__.py
kubernetes_py/models/__init__.py
kubernetes_py/models/unversioned/BaseModel.py
kubernetes_py/models/unversioned/BaseUrls.py
kubernetes_py/models/unversioned/ListMeta.py
kubernetes_py/models/unversioned/ListModel.py
kubernetes_py/models/unversioned/__init__.py
kubernetes_py/models/v1/AWSElasticBlockStoreVolumeSource.py
kubernetes_py/models/v1/Affinity.py
kubernetes_py/models/v1/AttachedVolume.py
kubernetes_py/models/v1/Capabilities.py
kubernetes_py/models/v1/ComponentCondition.py
kubernetes_py/models/v1/ComponentStatus.py
kubernetes_py/models/v1/ComponentStatusList.py
kubernetes_py/models/v1/ConfigMap.py
kubernetes_py/models/v1/ConfigMapEnvSource.py
kubernetes_py/models/v1/ConfigMapKeySelector.py
kubernetes_py/models/v1/ConfigMapProjection.py
kubernetes_py/models/v1/ConfigMapVolumeSource.py
kubernetes_py/models/v1/Container.py
kubernetes_py/models/v1/ContainerImage.py
kubernetes_py/models/v1/ContainerPort.py
kubernetes_py/models/v1/ContainerState.py
kubernetes_py/models/v1/ContainerStateRunning.py
kubernetes_py/models/v1/ContainerStateTerminated.py
kubernetes_py/models/v1/ContainerStateWaiting.py
kubernetes_py-1.10.14.dist-info/LICENSE.md
kubernetes_py-1.10.14.dist-info/METADATA
kubernetes_py-1.10.14.dist-info/WHEEL
kubernetes_py-1.10.14.dist-info/top_level.txt
kubernetes_py-1.10.14.dist-info/RECORD
